django_redis_sentinel/__init__.py
django_redis_sentinel/sentinel.py
sb_django_redis_sentinel-1.1.1.dist-info/LICENSE
sb_django_redis_sentinel-1.1.1.dist-info/METADATA
sb_django_redis_sentinel-1.1.1.dist-info/WHEEL
sb_django_redis_sentinel-1.1.1.dist-info/top_level.txt
sb_django_redis_sentinel-1.1.1.dist-info/RECORD
