Metadata-Version: 2.1
Name: sb-django-redis-sentinel
Version: 1.1.1
Summary: Plugin for django-redis that supports Redis Sentinel
Home-page: https://github.com/SpatialBuzz/django-redis-sentinel
Author: Ryan Shaw
Author-email: ryan.shaw@spatialbuzz.com
License: UNKNOWN
Platform: UNKNOWN
Classifier: Development Status :: 5 - Production/Stable
Classifier: Operating System :: OS Independent
Classifier: Environment :: Web Environment
Classifier: Framework :: Django
Classifier: License :: OSI Approved :: MIT License
Classifier: Intended Audience :: Developers
Classifier: Programming Language :: Python
Classifier: Programming Language :: Python :: 2
Classifier: Programming Language :: Python :: 2.7
Classifier: Programming Language :: Python :: 3
Classifier: Programming Language :: Python :: 3.2
Classifier: Programming Language :: Python :: 3.3
Classifier: Programming Language :: Python :: 3.4
Classifier: Topic :: Software Development :: Libraries
Classifier: Topic :: Utilities
Requires-Dist: django-redis (<=4.10.0,>=3.8.0)
Requires-Dist: Django (<3)
